littlehorse/__init__.py
littlehorse/auth.py
littlehorse/config.py
littlehorse/exceptions.py
littlehorse/model/__init__.py
littlehorse/model/acls_pb2.py
littlehorse/model/acls_pb2.pyi
littlehorse/model/common_enums_pb2.py
littlehorse/model/common_enums_pb2.pyi
littlehorse/model/common_wfspec_pb2.py
littlehorse/model/common_wfspec_pb2.pyi
littlehorse/model/external_event_pb2.py
littlehorse/model/external_event_pb2.pyi
littlehorse/model/node_run_pb2.py
littlehorse/model/node_run_pb2.pyi
littlehorse/model/object_id_pb2.py
littlehorse/model/object_id_pb2.pyi
littlehorse/model/output_topic_pb2.py
littlehorse/model/output_topic_pb2.pyi
littlehorse/model/scheduled_wf_run_pb2.py
littlehorse/model/scheduled_wf_run_pb2.pyi
littlehorse/model/service_pb2.py
littlehorse/model/service_pb2.pyi
littlehorse/model/service_pb2_grpc.py
littlehorse/model/struct_def_pb2.py
littlehorse/model/struct_def_pb2.pyi
littlehorse/model/task_def_pb2.py
littlehorse/model/task_def_pb2.pyi
littlehorse/model/task_run_pb2.py
littlehorse/model/task_run_pb2.pyi
littlehorse/model/user_tasks_pb2.py
littlehorse/model/user_tasks_pb2.pyi
littlehorse/model/variable_pb2.py
littlehorse/model/variable_pb2.pyi
littlehorse/model/wf_run_pb2.py
littlehorse/model/wf_run_pb2.pyi
littlehorse/model/wf_spec_pb2.py
littlehorse/model/wf_spec_pb2.pyi
littlehorse/model/workflow_event_pb2.py
littlehorse/model/workflow_event_pb2.pyi
littlehorse/utils.py
littlehorse/worker.py
littlehorse/workflow.py
littlehorse_client-0.15.1.dist-info/METADATA
littlehorse_client-0.15.1.dist-info/WHEEL
littlehorse_client-0.15.1.dist-info/RECORD
