Metadata-Version: 2.4
Name: littlehorse-client
Version: 0.15.1
Summary: LittleHorse is a high-performance microservice orchestration engine that allows developers to build scalable, maintainable, and observable applications
License: AGPLv3
Keywords: littlehorse
Author: LittleHorse
Author-email: engineering@littlehorse.io
Requires-Python: >=3.10,<3.14
Classifier: Programming Language :: Python :: 3.10
Classifier: Programming Language :: Python :: 3.11
Classifier: Programming Language :: Python :: 3.12
Classifier: Programming Language :: Python :: 3.13
Requires-Dist: authlib (>=1.6,<1.7)
Requires-Dist: grpcio (==1.69.0)
Requires-Dist: jproperties (>=2.1,<2.2)
Requires-Dist: protobuf (==6.32.1)
Requires-Dist: requests (>=2.32,<2.33)
Project-URL: Documentation, https://littlehorse.io/docs/server
Project-URL: Homepage, https://littlehorse.io
Project-URL: Repository, https://github.com/littlehorse-enterprises/littlehorse
Project-URL: issues, https://github.com/littlehorse-enterprises/littlehorse/issues
